pkiviewer/__init__.py
pkiviewer/__main__.py
pkiviewer/asn1/__init__.py
pkiviewer/asn1/decode_tbs_certlist.py
pkiviewer/asn1/load_specification.py
pkiviewer/asn1/specs/tbs_certlist.asn1
pkiviewer/config.py
pkiviewer/context.py
pkiviewer/io.py
pkiviewer/model/__init__.py
pkiviewer/model/certificate.py
pkiviewer/model/common.py
pkiviewer/model/crl.py
pkiviewer/model/extension/__init__.py
pkiviewer/model/extension/authority_information_access.py
pkiviewer/model/extension/authority_key_identifier.py
pkiviewer/model/extension/basic_constraints.py
pkiviewer/model/extension/certificate_policy.py
pkiviewer/model/extension/crl_distribution_points.py
pkiviewer/model/extension/crl_number.py
pkiviewer/model/extension/delta_crl_indicator.py
pkiviewer/model/extension/extended_key_usage.py
pkiviewer/model/extension/freshest_crl.py
pkiviewer/model/extension/inhibit_any_policy.py
pkiviewer/model/extension/issuer_alternative_name.py
pkiviewer/model/extension/issuing_distribution_point.py
pkiviewer/model/extension/key_usage.py
pkiviewer/model/extension/name_constraints.py
pkiviewer/model/extension/not_implemented_by_cryptography.py
pkiviewer/model/extension/ocsp_nocheck.py
pkiviewer/model/extension/precertificate_signed_certificate_timestamps.py
pkiviewer/model/extension/reasons.py
pkiviewer/model/extension/signed_certificate_timestamps.py
pkiviewer/model/extension/subject_alternative_name.py
pkiviewer/model/extension/subject_information_access.py
pkiviewer/model/extension/subject_key_identifier.py
pkiviewer/model/p12.py
pkiviewer/model/public_key/__init__.py
pkiviewer/model/public_key/dh.py
pkiviewer/model/public_key/dsa.py
pkiviewer/model/public_key/ed25519.py
pkiviewer/model/public_key/ed448.py
pkiviewer/model/public_key/elliptic_curve.py
pkiviewer/model/public_key/rsa.py
pkiviewer/model/unpack.py
pkiviewer/oid/__init__.py
pkiviewer/oid/enterprise-numbers.txt
pkiviewer/oid/names.py
pkiviewer/oid/pen.py
pkiviewer/py.typed
pkiviewer/types.py
pkiviewer/utils/__init__.py
pkiviewer-0.2.1.dist-info/LICENSE
pkiviewer-0.2.1.dist-info/METADATA
pkiviewer-0.2.1.dist-info/WHEEL
pkiviewer-0.2.1.dist-info/entry_points.txt
pkiviewer-0.2.1.dist-info/RECORD
