Metadata-Version: 2.1
Name: pkiviewer
Version: 0.2.1
Summary: PKI file viewer
Home-page: https://github.com/sffjunkie/pkiviewer
License: Apache-2.0
Author: Simon Kennedy
Author-email: sffjunkie+code@gmail.com
Requires-Python: >=3.10,<4.0
Classifier: License :: OSI Approved :: Apache Software License
Classifier: Programming Language :: Python :: 3
Classifier: Programming Language :: Python :: 3.10
Classifier: Programming Language :: Python :: 3.11
Requires-Dist: asn1tools (>=0.163.0,<0.164.0)
Requires-Dist: click (>=8.1.3,<9.0.0)
Requires-Dist: cryptography (>=37.0.4,<38.0.0)
Requires-Dist: rich (>=12.5.1,<13.0.0)
Requires-Dist: tomli (>=2.0.1,<3.0.0)
Project-URL: Issue Tracker, https://github.com/sffjunkie/pkiviewer/issues
Project-URL: Repository, https://github.com/sffjunkie/pkiviewer
